Metadata-Version: 2.4
Name: joow_image_processing
Version: 0.0.1
Summary: Image processing using skimage 'Fork da Karina'
Home-page: 
Author: Jonatas
Requires-Python: >=3.5
Requires-Dist: matplotlib
Requires-Dist: numpy
Requires-Dist: scikit-image>=0.16.1
Dynamic: author
Dynamic: description
Dynamic: description-content-type
Dynamic: requires-dist
Dynamic: requires-python
Dynamic: summary
